Metadata-Version: 1.1
Name: fastcalculator
Version: 1.0.0
Summary: A very basic calculator
Home-page: UNKNOWN
Author: Praveen
Author-email: praveen885127@gmail.com
License: UNKNOWN
Keywords: calcultors
Platform: UNKNOWN
Classifier: Development Status :: 5 - Production/Stable
Classifier: Intended Audience :: Education
Classifier: Operating System :: Microsoft :: Windows :: Windows 10
Classifier: License :: OSI Approved :: MIT License
Classifier: Programming Language :: Python :: 3
